memfabric_hybrid/VERSION
memfabric_hybrid/__init__.py
memfabric_hybrid/_pymf_hybrid.cpython-311-x86_64-linux-gnu.so
memfabric_hybrid/_pymf_transfer.cpython-311-x86_64-linux-gnu.so
memfabric_hybrid/lib/libmf_hybm_core.so
memfabric_hybrid/lib/libmf_smem.so
memfabric_hybrid.libs/libmf_hybm_core-a203f25d.so
memfabric_hybrid.libs/libmf_smem-ba311483.so
memfabric_hybrid-1.0.5.dist-info/METADATA
memfabric_hybrid-1.0.5.dist-info/WHEEL
memfabric_hybrid-1.0.5.dist-info/top_level.txt
memfabric_hybrid-1.0.5.dist-info/RECORD
